Metadata-Version: 2.1
Name: cy2py
Version: 1.1.6
Home-page: https://github.com/conker84/cy2py
Author: Andrea Santurbano
Author-email: santand@gmail.com
License: MIT
Classifier: Programming Language :: Python :: 3
Classifier: License :: OSI Approved :: MIT License
Classifier: Operating System :: OS Independent
Requires-Python: >=3.6
License-File: LICENSE
